ji_async_http_utils/__init__.py
ji_async_http_utils/aiohttp.py
ji_async_http_utils/httpx.py
ji_async_http_utils/py.typed
ji_async_http_utils-5.1.0.dist-info/WHEEL
ji_async_http_utils-5.1.0.dist-info/METADATA
ji_async_http_utils-5.1.0.dist-info/RECORD
