Metadata-Version: 2.3
Name: ji-async-http-utils
Version: 5.1.0
Summary: Async HTTP utilities using aiohttp and httpx.
Author: J.I. Cruz
Author-email: J.I. Cruz <ji@jicruz.com>
Requires-Dist: httpx>=0.28.1
Requires-Dist: aiohttp>=3.9.0
Requires-Dist: tqdm>=4.66.0
Requires-Python: >=3.10
